pyipptool-0.4.9.dist-info/DESCRIPTION.rst
pyipptool-0.4.9.dist-info/METADATA
pyipptool-0.4.9.dist-info/pydist.json
pyipptool-0.4.9.dist-info/WHEEL
pyipptool-0.4.9.dist-info/RECORD
pyipptool-0.4.9.dist-info/top_level.txt
pyipptool/__init__.py
pyipptool/schemas.py
pyipptool/widgets.py
pyipptool/core.py
pyipptool/config.py
pyipptool/forms.py
pyipptool/templates/ipp/group_tuple.pt
pyipptool/templates/ipp/constant_tuple.pt
pyipptool/templates/ipp/item.pt
pyipptool/templates/ipp/form.pt
