Metadata-Version: 2.0
Name: pyipptool
Version: 0.4.9
Summary: ipptool python wrapper
Home-page: https://github.com/ezeep/pyipptool
Author: Nicolas Delaby
Author-email: nicolas.delaby@ezeep.com
License: Apache Software License
Platform: UNKNOWN
Classifier: Development Status :: 4 - Beta
Classifier: Intended Audience :: Developers
Classifier: Intended Audience :: System Administrators
Classifier: License :: OSI Approved :: Apache Software License
Classifier: Operating System :: OS Independent
Classifier: Programming Language :: Python :: 2.7
Classifier: Topic :: Printing
Requires-Dist: deform (>=2.0a2)
